bgr2grey/__init__.py
bgr2grey/bgr2grey.py
bgr2grey-1.0.1.dist-info/LICENSE
bgr2grey-1.0.1.dist-info/METADATA
bgr2grey-1.0.1.dist-info/WHEEL
bgr2grey-1.0.1.dist-info/top_level.txt
bgr2grey-1.0.1.dist-info/RECORD
