Metadata-Version: 2.1
Name: bgr2grey
Version: 1.0.1
Summary: A package for converting RGB images to grayscale
Home-page: https://github.com/divagarn/bgr2grey.git
Author: Divagar N
Author-email: divagar2kn@gmail.com
License: MIT
License-File: LICENSE
Requires-Dist: numpy
